lsv_panel-0.1.0.dist-info/METADATA
lsv_panel-0.1.0.dist-info/WHEEL
lsv_panel-0.1.0.dist-info/licenses/LICENSE
lsv_panel.libs/libgcc_s-5b5488a6.so.1
lsv_panel/__init__.py
lsv_panel/lsv_panel.cpython-313-arm-linux-musleabihf.so
lsv_panel-0.1.0.dist-info/RECORD
