Metadata-Version: 2.4
Name: lsv-panel
Version: 0.1.0
Classifier: Programming Language :: Rust
Classifier: Programming Language :: Python :: Implementation :: CPython
Classifier: Programming Language :: Python :: Implementation :: PyPy
Requires-Dist: maturin ; extra == 'build'
Requires-Dist: maturin ; extra == 'dev'
Requires-Dist: matplotlib ; extra == 'dev'
Requires-Dist: numpy>=1.8 ; extra == 'dev'
Requires-Dist: pytest ; extra == 'dev'
Provides-Extra: build
Provides-Extra: dev
License-File: LICENSE
Summary: Linear strength vortex panel method from Katz & Plotkin, implemented in Rust with a Python API
Requires-Python: >=3.8
